Lab3/NET_D_FF/Lab3_SR_Latch_gatelevel.v
module Lab3_SR_Latch_gatelevel(output Q, NQ, input S, R);
	
	nor #(2) r(Q, R, NQ);
	nor #(2) s(NQ, S, Q);

endmodule

Lab3/NET_D_FF/Lab3_Neg_Edge_D_FF_gatelevel.v
module Lab3_Neg_Edge_D_FF_gatelevel (output Q, NQ, input D, clock);

	wire o1, o4;
	wire R, S;

	nor #(2) g1(o1, o4, R);
	nor #(2) g2(R, o1, clock);
	nor #(2) g3(S, R, clock, o4);
	nor #(2) g4(o4, S, D);

	Lab3_SR_Latch_gatelevel M(Q, NQ, S, R);

endmodule

Lab3/NET_D_FF/t_Lab3_Neg_Edge_D_FF_gatelevel.v
module t_Lab3_Neg_Edge_D_FF_gatelevel;
	reg clock, D;
	wire Q, NQ;	


	Lab3_Neg_Edge_D_FF_gatelevel M(Q, NQ, D, clock);

	initial #200 $finish;

	initial begin
		clock = 1'b0;
		forever #10 clock = ~clock;
	end

	initial fork
		 #00 D = 0;
		 #15 D = 1;
		 #35 D = 0;
		 #65 D = 1;
		 #88 D = 0;
		 #125 D = 1;
		 #130 D = 0;
	join

	initial begin
		$dumpfile("Neg_Edge_D_FF_gatelevel.vcd");
		$dumpvars;
	end

endmodule

Lab3/NET_D_FF/Neg_Edge_D_FF_gatelevel.vcd
$date
	Sun Jun 14 11:57:55 2020
$end
$version
	Icarus Verilog
$end
$timescale
	1s
$end
$scope module t_Lab3_Neg_Edge_D_FF_gatelevel $end
$var wire 1 ! Q $end
$var wire 1 " NQ $end
$var reg 1 # D $end
$var reg 1 $ clock $end
$scope module M $end
$var wire 1 # D $end
$var wire 1 % R $end
$var wire 1 & S $end
$var wire 1 $ clock $end
$var wire 1 ' o1 $end
$var wire 1 ( o4 $end
$var wire 1 ! Q $end
$var wire 1 " NQ $end
$scope module M $end
$var wire 1 " NQ $end
$var wire 1 ! Q $end
$var wire 1 % R $end
$var wire 1 & S $end
$upscope $end
$upscope $end
$upscope $end
$enddefinitions $end
#0
$dumpvars
x(
x'
x&
x%
0$
0#
x"
x!
$end
#10
1$
#12
0%
0&
#14
1(
#15
1#
#16
0'
#17
0(
#19
1'
#20
0$
#22
1&
#24
0"
#26
1!
#30
1$
#32
0&
#35
0#
#37
1(
#39
0'
#40
0$
#42
1%
#44
0!
#46
1"
#50
1$
#52
0%
#60
0$
#62
1%
#65
1#
#67
0(
#70
1$
#72
0%
#74
1'
#80
0$
#82
1&
#84
0"
#86
1!
#88
0#
#90
1$
#92
0&
#94
1(
#96
0'
#100
0$
#102
1%
#104
0!
#106
1"
#110
1$
#112
0%
#120
0$
#122
1%
#125
1#
#127
0(
#130
1$
0#
#132
0%
1(
#140
0$
#142
1%
#150
1$
#152
0%
#160
0$
#162
1%
#170
1$
#172
0%
#180
0$
#182
1%
#190
1$
#192
0%
