Lab1/Lab1_dataflow.v
module	Lab1_dataflow(F, A, B, C, D);
	output F;
	input A, B, C, D;
	
	wire negD, negB, negA;
	wire andAD, andBC, andCD;
	wire orTwoAnd, orACD;

	assign negD = !D;
	assign negB = !B;
	assign negA = !A;

	assign andAD = A & negD;
	assign andBC = negB & C;
	assign andCD = C & D;

	assign orTwoAnd = andAD | andBC;
	assign orACD = negA | andCD;

	assign F = orTwoAnd & orACD;

endmodule

Lab1/t_Lab1_dataflow.v
module	t_Lab1_dataflow;
	wire	F;
	reg   A, B, C, D;
	
	//instantiate device under test
	Lab1_dataflow M1(F, A, B, C, D);
	
	//apply inputs one at a time
	initial	begin
		$dumpfile("Lab1_dataflow.vcd");
    	$dumpvars;

    	A = 1'b0; B = 1'b0; C = 1'b0; D = 1'b0;
    	#50 A = 1'b0; B = 1'b0; C = 1'b0; D = 1'b1;
    	
    	#50 A = 1'b0; B = 1'b0; C = 1'b1; D = 1'b0;
    	#50 A = 1'b0; B = 1'b0; C = 1'b1; D = 1'b1;

    	#50 A = 1'b0; B = 1'b1; C = 1'b0; D = 1'b0;
    	#50 A = 1'b0; B = 1'b1; C = 1'b0; D = 1'b1;
    	#50 A = 1'b0; B = 1'b1; C = 1'b1; D = 1'b0;
    	#50 A = 1'b0; B = 1'b1; C = 1'b1; D = 1'b1;

    	#50 A = 1'b1; B = 1'b0; C = 1'b0; D = 1'b0;
    	#50 A = 1'b1; B = 1'b0; C = 1'b0; D = 1'b1;
    	#50 A = 1'b1; B = 1'b0; C = 1'b1; D = 1'b0;
    	#50 A = 1'b1; B = 1'b0; C = 1'b1; D = 1'b1;

    	#50 A = 1'b1; B = 1'b1; C = 1'b0; D = 1'b0;
    	#50 A = 1'b1; B = 1'b1; C = 1'b0; D = 1'b1;
    	#50 A = 1'b1; B = 1'b1; C = 1'b1; D = 1'b0;
    	#50 A = 1'b1; B = 1'b1; C = 1'b1; D = 1'b1;
    end
    	
	initial #800 $finish;

endmodule

Lab1/Lab1_dataflow.vcd
$date
	Sun May  3 23:34:10 2020
$end
$version
	Icarus Verilog
$end
$timescale
	1s
$end
$scope module t_Lab1_dataflow $end
$var wire 1 ! F $end
$var reg 1 " A $end
$var reg 1 # B $end
$var reg 1 $ C $end
$var reg 1 % D $end
$scope module M1 $end
$var wire 1 " A $end
$var wire 1 # B $end
$var wire 1 $ C $end
$var wire 1 % D $end
$var wire 1 ! F $end
$var wire 1 & andAD $end
$var wire 1 ' andBC $end
$var wire 1 ( andCD $end
$var wire 1 ) orACD $end
$var wire 1 * orTwoAnd $end
$var wire 1 + negD $end
$var wire 1 , negB $end
$var wire 1 - negA $end
$upscope $end
$upscope $end
$enddefinitions $end
#0
$dumpvars
1-
1,
1+
0*
1)
0(
0'
0&
0%
0$
0#
0"
0!
$end
#50
0+
1%
#100
1!
1*
1'
1+
0%
1$
#150
1(
0+
1%
#200
0!
0*
0(
0'
1+
0%
0$
0,
1#
#250
0+
1%
#300
1+
0%
1$
#350
1(
0+
1%
#400
0)
1*
0(
1&
1+
0%
0$
1,
0#
0-
1"
#450
0*
0&
0+
1%
#500
1*
1&
1'
1+
0%
1$
#550
1!
1)
1(
0&
0+
1%
#600
0!
0)
1&
0(
0'
1+
0%
0$
0,
1#
#650
0*
0&
0+
1%
#700
1*
1&
1+
0%
1$
#750
1)
0*
1(
0&
0+
1%
