Lab3/Melay-Type/D_ff_AR.v
module D_ff_AR(output reg Q, input D, clk, rst);
	
	// reset active LOW
	always @(posedge clk, negedge rst) begin
		if (!rst) Q <= 1'b0;
		else Q <= D;
	end

endmodule

Lab3/Melay-Type/Lab3_BCD_to_Excess3_structure.v
module Lab3_BCD_to_Excess3_structure(output z, input x, clock, reset);
	
	wire Q2, Q1, Q0;
	wire D2, D1, D0;

	assign D2 = Q1&Q0 + (~Q2)&Q1 + x&(~Q2)&Q0 + Q2&(~Q1)&(~Q0);

	assign D1 = x&(~Q1)&(~Q0) + (~x)&(~Q2)&(~Q1)&Q0;
	
	assign D0 = Q1&Q0 + (~x)&(~Q2)&(~Q1);
	
	assign  z = (~x)&(~Q2)&(~Q1) + x&Q1 + Q2&Q1 + x&Q2&Q0;

	D_ff_AR M2(Q2, D2, clock, reset);
	D_ff_AR M1(Q1, D1, clock, reset);
	D_ff_AR M0(Q0, D1, clock, reset);

endmodule

Lab3/Melay-Type/Lab3_BCD_to_Excess3 _state_diagram.v
module Lab3_BCD_to_Excess3_state_diagram(output reg z, input x, clock, reset);
	
	parameter S0 = 3'b000, S1 = 3'b001, S2 = 3'b010, S3 = 3'b011;
	parameter S4 = 3'b100, S5 = 3'b101, S6 = 3'b110;

	reg [2:0] now_state, nxt_state;

	always @(posedge clock, negedge reset) 
		if (reset == 1'b0) now_state <= S0;
		else now_state <= nxt_state;

	always @(now_state, x)
		case (now_state)
			S0: if (x) nxt_state = S2; else nxt_state = S1;
			S1: if (x) nxt_state = S4; else nxt_state = S3;
			S2: nxt_state = S4;
			S3: nxt_state = S5;
			S4: if (x) nxt_state = S6; else nxt_state = S5;
			S5: nxt_state = S0;
			S6: nxt_state = S0;
		endcase

	always @(now_state, x)
		case (now_state)
			S0, S1, S4, S6: z = ~x;
			S2, S3, S5: z = x;
		endcase
		

endmodule

Lab3/Melay-Type/t_Lab3_BCD_to_Excess3.v
module t_Lab3_BCD_to_Excess3;
	
	reg [3:0] num;
	reg x, clk;
	reg rst;    // active LOW
	reg idx;
	wire z1, z2;

	reg [3:0] std, str;

	Lab3_BCD_to_Excess3_state_diagram M1(z1, x, clk, rst);
	Lab3_BCD_to_Excess3_structure M2(z2, x, clk, rst);

	initial #400 $finish;

	initial begin
		$dumpfile("BCD_to_Excess3.vcd");
		$dumpvars;
	end

	initial begin
		clk = 1'b1;
		forever #5 clk = ~clk;
	end

	// initial begin
	// 	#5 rst = 1'b0;
	// 	#5 rst = 1'b1;
	// end

	// initial begin
	// 	num = 4'b0000;
	// 	std = 4'b0000;
	// 	str = 4'b0000;

	// 	#10 x = 1'b0;

	// 	repeat(10) begin
	// 		$display("\nBCD: %b%b%b%b", num[3], num[2], num[1], num[0]);

	// 		rst = 1'b1;
	// 			x = num[0]; std[0] = z1; str[0] = z2;
	// 		#10 x = num[1]; std[1] = z1; str[1] = z2;
	// 		#10 x = num[2]; std[2] = z1; str[2] = z2;
	// 		#10 x = num[3]; std[3] = z1; str[3] = z2;

	// 		$write("State: %b%b%b%b\n", std[3], std[2], std[1], std[0]);
	// 		$write("Struct: %b%b%b%b\n", str[3], str[2], str[1], str[0]);
		
	// 		#5 rst = 1'b0;
	// 		#5 rst = 1'b1;

 // 			num = num + 4'b0001;
	// 	end
	// end

	initial begin
		rst = 1'b1;
		#1 rst = 1'b0;
		#1 rst = 1'b1;
	end

	initial begin 
		    x = 0;
		#10 x = 0;
		#10 x = 0;
		#10 x = 0;

		#10 x = 1;
		#10 x = 0;
		#10 x = 0;
		#10 x = 0;

		#10 x = 0;
		#10 x = 1;
		#10 x = 0;
		#10 x = 1;

		#10 x = 1;
		#10 x = 1;
		#10 x = 0;
		#10 x = 0;

		#10 x = 0;
		#10 x = 1;
		#10 x = 0;
		#10 x = 0;

		#10 x = 0;
		#10 x = 0;
		#10 x = 0;
		#10 x = 1;

		#10 x = 0;
		#10 x = 0;
		#10 x = 1;
		#10 x = 1;

		#10 x = 0;
		#10 x = 1;
		#10 x = 1;
		#10 x = 1;
		
		#10 x = 1;
		#10 x = 0;
		#10 x = 0;
		#10 x = 1;

		#10 x = 1;
		#10 x = 0;
		#10 x = 1;
		#10 x = 0;
	end

endmodule

Lab3/Melay-Type/BCD_to_Excess3.vcd
$date
	Sun Jun 14 21:08:06 2020
$end
$version
	Icarus Verilog
$end
$timescale
	1s
$end
$scope module t_Lab3_BCD_to_Excess3 $end
$var wire 1 ! z2 $end
$var wire 1 " z1 $end
$var reg 1 # clk $end
$var reg 1 $ rst $end
$var reg 1 % x $end
$scope module M1 $end
$var wire 1 # clock $end
$var wire 1 $ reset $end
$var wire 1 % x $end
$var reg 3 & now_state [2:0] $end
$var reg 3 ' nxt_state [2:0] $end
$var reg 1 " z $end
$upscope $end
$scope module M2 $end
$var wire 1 ( D0 $end
$var wire 1 ) D1 $end
$var wire 1 * D2 $end
$var wire 1 # clock $end
$var wire 1 $ reset $end
$var wire 1 % x $end
$var wire 1 ! z $end
$var wire 1 + Q2 $end
$var wire 1 , Q1 $end
$var wire 1 - Q0 $end
$scope module M0 $end
$var wire 1 ) D $end
$var wire 1 # clk $end
$var wire 1 $ rst $end
$var reg 1 - Q $end
$upscope $end
$scope module M1 $end
$var wire 1 ) D $end
$var wire 1 # clk $end
$var wire 1 $ rst $end
$var reg 1 , Q $end
$upscope $end
$scope module M2 $end
$var wire 1 * D $end
$var wire 1 # clk $end
$var wire 1 $ rst $end
$var reg 1 + Q $end
$upscope $end
$upscope $end
$upscope $end
$enddefinitions $end
#0
$dumpvars
0-
0,
x+
0*
0)
0(
bx '
bx &
0%
1$
1#
x"
0!
$end
#1
b1 '
1"
0+
b0 &
0$
#2
1$
#5
0#
#10
b11 '
b1 &
1#
#15
0#
#20
b101 '
0"
b11 &
1#
#25
0#
#30
b0 '
b101 &
1#
#35
0#
#40
b10 '
b0 &
0"
1#
1%
#45
0#
#50
b1 &
b11 '
1"
1#
0%
#55
0#
#60
b101 '
0"
b11 &
1#
#65
0#
#70
b0 '
b101 &
1#
#75
0#
#80
b1 '
1"
b0 &
1#
#85
0#
#90
b10 &
1"
b100 '
1#
1%
#95
0#
#100
b101 '
b100 &
1"
1#
0%
#105
0#
#110
b110 &
0"
b0 '
1#
1%
#115
0#
#120
b10 '
b0 &
1#
#125
0#
#130
b100 '
1"
b10 &
1#
#135
0#
#140
b101 '
b100 &
1"
1#
0%
#145
0#
#150
0"
b0 '
b101 &
1#
#155
0#
#160
b1 '
1"
b0 &
1#
#165
0#
#170
b10 &
1"
b100 '
1#
1%
#175
0#
#180
b101 '
b100 &
1"
1#
0%
#185
0#
#190
0"
b0 '
b101 &
1#
#195
0#
#200
b1 '
1"
b0 &
1#
#205
0#
#210
b11 '
b1 &
1#
#215
0#
#220
b101 '
0"
b11 &
1#
#225
0#
#230
b0 '
b101 &
1"
1#
1%
#235
0#
#240
b1 '
b0 &
1"
1#
0%
#245
0#
#250
b11 '
b1 &
1#
#255
0#
#260
b100 &
b110 '
0"
1#
1%
#265
0#
#270
b0 '
b110 &
1#
#275
0#
#280
b1 '
b0 &
1"
1#
0%
#285
0#
#290
b10 &
1"
b100 '
1#
1%
#295
0#
#300
0"
b110 '
b100 &
1#
#305
0#
#310
b0 '
b110 &
1#
#315
0#
#320
b10 '
b0 &
1#
#325
0#
#330
b1 &
b11 '
1"
1#
0%
#335
0#
#340
b101 '
0"
b11 &
1#
#345
0#
#350
b0 '
b101 &
1"
1#
1%
#355
0#
#360
0"
b10 '
b0 &
1#
#365
0#
#370
b1 &
b11 '
1"
1#
0%
#375
0#
#380
b100 &
b110 '
0"
1#
1%
#385
0#
#390
b101 &
b0 '
0"
1#
0%
#395
0#
#400
b1 '
1"
b0 &
1#
