Lab2/Lab2_CLG_behavior.v
module Lab2_CLG_behavior(C, P, G, C0);
	
	output reg [4:1] C;
	input  [3:0] P, G;
	input  C0;

	always @(*) begin
		C[1] = (P[0]&C0) | G[0];
		C[2] = (P[1]&P[0]&C0) | (P[1]&G[0]) | G[1];
		C[3] = (P[2]&P[1]&P[0]&C0) | (P[2]&P[1]&G[0]) | (G[1]&P[2]) | G[2];
		C[4] = (P[3]&P[2]&P[1]&P[0]&C0) | (P[3]&P[2]&P[1]&G[0]) | (P[3]&G[1]&P[2]) | (P[3]&G[2]) | G[3];
	end

endmodule

Lab2/Lab2_4_bit_BLS.v
module Lab2_4_bit_BLS(Diff, Bout, X, Y, Bin);
	
	output reg [3:0] Diff;
	output reg Bout;
	input [3:0] X, Y;
	input Bin;

	wire [4:1] C;
	wire [3:0] P, G;

	assign P = ~(X ^ Y);
	assign G = ~X & Y;

	// module Lab2_CLG_behavior(C, P, G, C0);
	Lab2_CLG_behavior M(C, P, G, Bin);

	always @(*) begin
		Diff[0] = ~P[0] ^ Bin;
		Diff[1] = ~P[1] ^ C[1];
		Diff[2] = ~P[2] ^ C[2];
		Diff[3] = ~P[3] ^ C[3];
		Bout = C[4];
	end

endmodule

Lab2/t_Lab2_4_bit_BLS.v
module t_Lab2_4_bit_BLS;

	wire [3:0] Diff;
	wire Bout;
	reg [3:0] X, Y;
	reg Bin;

	Lab2_4_bit_BLS M(Diff, Bout, X, Y, Bin);

	initial begin
		$dumpfile("Lab2_4_bit_BLS.vcd");
		$dumpvars;

			X = 4'b1101; Y = 4'b0101; Bin = 1'b0;
		#50 X = 4'b1100; Y = 4'b1000; Bin = 1'b1;
		
		#50 X = 4'b0101; Y = 4'b1101; Bin = 1'b0;
		#50 X = 4'b1000; Y = 4'b1100; Bin = 1'b1;

		#50 X = 4'b0101; Y = 4'b0101; Bin = 1'b0;
		#50 X = 4'b1011; Y = 4'b1011; Bin = 1'b1;

		#50 X = 4'b0000; Y = 4'b1111; Bin = 1'b0;
		#50 X = 4'b0000; Y = 4'b1111; Bin = 1'b1;
	end

	initial begin
		$display("B Dif");
		$monitor("%b %b%b%b%b", Bout, Diff[3], Diff[2], Diff[1], Diff[0]);
	end

endmodule

Lab2/BLS Result/Lab2_4_bit_BLS.vcd
$date
	Mon May 25 12:21:21 2020
$end
$version
	Icarus Verilog
$end
$timescale
	1s
$end
$scope module t_Lab2_4_bit_BLS $end
$var wire 4 ! Diff [3:0] $end
$var wire 1 " Bout $end
$var reg 1 # Bin $end
$var reg 4 $ X [3:0] $end
$var reg 4 % Y [3:0] $end
$scope module M $end
$var wire 1 # Bin $end
$var wire 4 & G [3:0] $end
$var wire 4 ' P [3:0] $end
$var wire 4 ( X [3:0] $end
$var wire 4 ) Y [3:0] $end
$var wire 4 * C [4:1] $end
$var reg 1 " Bout $end
$var reg 4 + Diff [3:0] $end
$scope module M $end
$var wire 1 # C0 $end
$var wire 4 , G [3:0] $end
$var wire 4 - P [3:0] $end
$var reg 4 . C [4:1] $end
$upscope $end
$upscope $end
$upscope $end
$enddefinitions $end
#0
$dumpvars
b0 .
b111 -
b0 ,
b1000 +
b0 *
b101 )
b1101 (
b111 '
b0 &
b101 %
b1101 $
0#
0"
b1000 !
$end
#50
b1011 '
b1011 -
b11 *
b11 .
b11 !
b11 +
1#
b1000 %
b1000 )
b1100 $
b1100 (
#100
1"
b111 '
b111 -
b1000 *
b1000 .
b1000 !
b1000 +
b1000 &
b1000 ,
0#
b1101 %
b1101 )
b101 $
b101 (
#150
1"
b1011 '
b1011 -
b1111 *
b1111 .
b1011 !
b1011 +
b100 &
b100 ,
1#
b1100 %
b1100 )
b1000 $
b1000 (
#200
0"
b1111 '
b1111 -
b0 *
b0 .
b0 !
b0 +
b0 &
b0 ,
0#
b101 %
b101 )
b101 $
b101 (
#250
1"
b1111 *
b1111 .
b1111 !
b1111 +
1#
b1011 %
b1011 )
b1011 $
b1011 (
#300
b0 '
b0 -
b1 !
b1 +
b1111 &
b1111 ,
0#
b1111 %
b1111 )
b0 $
b0 (
#350
b0 !
b0 +
1#
