Lab2/Lab2_CLG_behavior.v
module Lab2_CLG_behavior(C, P, G, C0);
	
	output reg [4:1] C;
	input  [3:0] P, G;
	input  C0;

	always @(*) begin
		C[1] = (P[0]&C0) | G[0];
		C[2] = (P[1]&P[0]&C0) | (P[1]&G[0]) | G[1];
		C[3] = (P[2]&P[1]&P[0]&C0) | (P[2]&P[1]&G[0]) | (G[1]&P[2]) | G[2];
		C[4] = (P[3]&P[2]&P[1]&P[0]&C0) | (P[3]&P[2]&P[1]&G[0]) | (P[3]&G[1]&P[2]) | (P[3]&G[2]) | G[3];
	end

endmodule

Lab2/Lab2_4_bit_CLA.v
module Lab2_4_bit_CLA(Sum, Cout, A, B, Cin);

	output reg [3:0] Sum;
	output reg Cout;

	input [3:0] A, B;
	input Cin;

	wire [4:1] C;
	wire [3:0] P, G;

	assign P = A ^ B;
	assign G = A & B;

	// module Lab2_CLG_behavior(C, P, G, C0);
	Lab2_CLG_behavior M(C, P, G, Cin);

	always @(*) begin
		Sum[0] = P[0] ^ Cin;
		Sum[1] = P[1] ^ C[1];
		Sum[2] = P[2] ^ C[2];
		Sum[3] = P[3] ^ C[3];
		Cout = C[4];
	end
	
endmodule

Lab2/t_Lab2_4_bit_CLA.v
module t_Lab2_4_bit_CLA;
	wire [3:0] Sum;
	wire Cout;

	reg [3:0] A, B;
	reg Cin;

	Lab2_4_bit_CLA M(Sum, Cout, A, B, Cin);

	initial #400 $finish;

	initial begin
		$dumpfile("Lab2_4_bit_CLA.vcd");
		$dumpvars;
		
			A = 4'b1101; B = 4'b0101; Cin = 1'b0;
		#50 A = 4'b1100; B = 4'b1000; Cin = 1'b1;
		
		#50 A = 4'b0101; B = 4'b1101; Cin = 1'b0;
		#50 A = 4'b1000; B = 4'b1100; Cin = 1'b1;

		#50 A = 4'b0101; B = 4'b0101; Cin = 1'b0;
		#50 A = 4'b1011; B = 4'b1011; Cin = 1'b1;

		#50 A = 4'b1111; B = 4'b1111; Cin = 1'b1;
		#50 A = 4'b1111; B = 4'b0000; Cin = 1'b1;
	end

	initial begin
		$display("C Sum");
		$monitor("%b %b%b%b%b", Cout, Sum[3], Sum[2], Sum[1], Sum[0]);
	end

endmodule

Lab2/CLG Result/Lab2_4_bit_CLA.vcd
$date
	Mon May 25 13:25:20 2020
$end
$version
	Icarus Verilog
$end
$timescale
	1s
$end
$scope module t_Lab2_4_bit_CLA $end
$var wire 4 ! Sum [3:0] $end
$var wire 1 " Cout $end
$var reg 4 # A [3:0] $end
$var reg 4 $ B [3:0] $end
$var reg 1 % Cin $end
$scope module M $end
$var wire 4 & A [3:0] $end
$var wire 4 ' B [3:0] $end
$var wire 1 % Cin $end
$var wire 4 ( G [3:0] $end
$var wire 4 ) P [3:0] $end
$var wire 4 * C [4:1] $end
$var reg 1 " Cout $end
$var reg 4 + Sum [3:0] $end
$scope module M $end
$var wire 1 % C0 $end
$var wire 4 , G [3:0] $end
$var wire 4 - P [3:0] $end
$var reg 4 . C [4:1] $end
$upscope $end
$upscope $end
$upscope $end
$enddefinitions $end
#0
$dumpvars
b1101 .
b1000 -
b101 ,
b10 +
b1101 *
b1000 )
b101 (
b101 '
b1101 &
0%
b101 $
b1101 #
1"
b10 !
$end
#50
b1000 *
b1000 .
b101 !
b101 +
b100 )
b100 -
b1000 (
b1000 ,
1%
b1000 $
b1000 '
b1100 #
b1100 &
#100
b1101 *
b1101 .
b10 !
b10 +
b1000 )
b1000 -
b101 (
b101 ,
0%
b1101 $
b1101 '
b101 #
b101 &
#150
b1000 *
b1000 .
b101 !
b101 +
b100 )
b100 -
b1000 (
b1000 ,
1%
b1100 $
b1100 '
b1000 #
b1000 &
#200
0"
b101 *
b101 .
b1010 !
b1010 +
b0 )
b0 -
b101 (
b101 ,
0%
b101 $
b101 '
b101 #
b101 &
#250
1"
b1011 *
b1011 .
b111 !
b111 +
b1011 (
b1011 ,
1%
b1011 $
b1011 '
b1011 #
b1011 &
#300
b1111 !
b1111 +
b1111 *
b1111 .
b1111 (
b1111 ,
b1111 $
b1111 '
b1111 #
b1111 &
#350
b0 !
b0 +
b1111 )
b1111 -
b0 (
b0 ,
b0 $
b0 '
